{
    "date": "1987-05-30",
    "data": [
        {
            "song": "Head To Toe",
            "artist": "Lisa Lisa And Cult Jam",
            "this_week": 1,
            "last_week": 2,
            "peak_position": 1,
            "weeks_on_chart": 6
        },
        {
            "song": "The Pleasure Principle (Remix)",
            "artist": "Janet Jackson",
            "this_week": 2,
            "last_week": 4,
            "peak_position": 2,
            "weeks_on_chart": 4
        },
        {
            "song": "Certain Things Are Likely (Remix)",
            "artist": "K.T.P.",
            "this_week": 3,
            "last_week": 1,
            "peak_position": 1,
            "weeks_on_chart": 9
        },
        {
            "song": "Let's Work It Out",
            "artist": "Sadie Nine",
            "this_week": 4,
            "last_week": 5,
            "peak_position": 4,
            "weeks_on_chart": 7
        },
        {
            "song": "Each Time You Break My Heart (Remix)",
            "artist": "Nick Kamen",
            "this_week": 5,
            "last_week": 9,
            "peak_position": 5,
            "weeks_on_chart": 7
        },
        {
            "song": "Diamonds (Remix)",
            "artist": "Herb Alpert",
            "this_week": 6,
            "last_week": 25,
            "peak_position": 6,
            "weeks_on_chart": 2
        },
        {
            "song": "Something In My House",
            "artist": "Dead Or Alive",
            "this_week": 7,
            "last_week": 3,
            "peak_position": 3,
            "weeks_on_chart": 12
        },
        {
            "song": "Don't Blow A Good Thing (Remix)",
            "artist": "Vesta",
            "this_week": 8,
            "last_week": 16,
            "peak_position": 8,
            "weeks_on_chart": 4
        },
        {
            "song": "Mr. Right",
            "artist": "Eleanor Mills",
            "this_week": 9,
            "last_week": 7,
            "peak_position": 7,
            "weeks_on_chart": 9
        },
        {
            "song": "Sometimes (Remix)/It Doesn't Have To Be",
            "artist": "Erasure",
            "this_week": 10,
            "last_week": 23,
            "peak_position": 10,
            "weeks_on_chart": 3
        },
        {
            "song": "Day-In Day-Out(Remix)",
            "artist": "David Bowie",
            "this_week": 11,
            "last_week": 11,
            "peak_position": 11,
            "weeks_on_chart": 6
        },
        {
            "song": "Respectable (Remix)",
            "artist": "Mel & Kim",
            "this_week": 12,
            "last_week": 24,
            "peak_position": 12,
            "weeks_on_chart": 3
        },
        {
            "song": "Just Another Man",
            "artist": "Jeanne Harris",
            "this_week": 13,
            "last_week": 13,
            "peak_position": 13,
            "weeks_on_chart": 6
        },
        {
            "song": "Let's Have Some Fun",
            "artist": "Merge Featuring Debbie A.",
            "this_week": 14,
            "last_week": 17,
            "peak_position": 14,
            "weeks_on_chart": 4
        },
        {
            "song": "Communicate",
            "artist": "Full House",
            "this_week": 15,
            "last_week": 22,
            "peak_position": 15,
            "weeks_on_chart": 5
        },
        {
            "song": "Don't Look Now/Can't Find My Way Home",
            "artist": "Torch Song",
            "this_week": 16,
            "last_week": 15,
            "peak_position": 15,
            "weeks_on_chart": 6
        },
        {
            "song": "In Love With Love (Remix)",
            "artist": "Debbie Harry",
            "this_week": 17,
            "last_week": 30,
            "peak_position": 17,
            "weeks_on_chart": 2
        },
        {
            "song": "Big Love (Remix)",
            "artist": "Fleetwood Mac",
            "this_week": 18,
            "last_week": 34,
            "peak_position": 18,
            "weeks_on_chart": 2
        },
        {
            "song": "Macho Mozart",
            "artist": "Latin Rascals",
            "this_week": 19,
            "last_week": 14,
            "peak_position": 14,
            "weeks_on_chart": 7
        },
        {
            "song": "Lessons In Love (Remix)",
            "artist": "Level 42",
            "this_week": 20,
            "last_week": 28,
            "peak_position": 20,
            "weeks_on_chart": 5
        },
        {
            "song": "No One Knows (Remix)",
            "artist": "The Wild Marys",
            "this_week": 21,
            "last_week": 10,
            "peak_position": 10,
            "weeks_on_chart": 8
        },
        {
            "song": "My Heart Gets All The Breaks",
            "artist": "Monet",
            "this_week": 22,
            "last_week": 32,
            "peak_position": 22,
            "weeks_on_chart": 4
        },
        {
            "song": "Let Yourself Go",
            "artist": "Sybil",
            "this_week": 23,
            "last_week": 26,
            "peak_position": 23,
            "weeks_on_chart": 5
        },
        {
            "song": "Red Rose",
            "artist": "Alphaville",
            "this_week": 24,
            "last_week": 29,
            "peak_position": 24,
            "weeks_on_chart": 5
        },
        {
            "song": "Last Chance",
            "artist": "Cyre",
            "this_week": 25,
            "last_week": 8,
            "peak_position": 4,
            "weeks_on_chart": 11
        },
        {
            "song": "Rock-A-Lott (Remix)",
            "artist": "Aretha Franklin",
            "this_week": 26,
            "last_week": null,
            "peak_position": 26,
            "weeks_on_chart": 1
        },
        {
            "song": "Heart And Soul",
            "artist": "T'Pau",
            "this_week": 27,
            "last_week": 38,
            "peak_position": 27,
            "weeks_on_chart": 3
        },
        {
            "song": "Without You",
            "artist": "Touch",
            "this_week": 28,
            "last_week": 12,
            "peak_position": 11,
            "weeks_on_chart": 9
        },
        {
            "song": "Sign 'O' The Times",
            "artist": "Prince",
            "this_week": 29,
            "last_week": 6,
            "peak_position": 2,
            "weeks_on_chart": 11
        },
        {
            "song": "Why Should I Cry (Remix)",
            "artist": "Nona Hendryx",
            "this_week": 30,
            "last_week": 39,
            "peak_position": 30,
            "weeks_on_chart": 2
        },
        {
            "song": "American Soviets",
            "artist": "C.C.C.P.",
            "this_week": 31,
            "last_week": 33,
            "peak_position": 31,
            "weeks_on_chart": 6
        },
        {
            "song": "January,February",
            "artist": "Tina B.",
            "this_week": 32,
            "last_week": 20,
            "peak_position": 16,
            "weeks_on_chart": 8
        },
        {
            "song": "Modigliani (Lost In Your Eyes)(Remix)",
            "artist": "Book Of Love",
            "this_week": 33,
            "last_week": null,
            "peak_position": 33,
            "weeks_on_chart": 1
        },
        {
            "song": "Second Chance For Love",
            "artist": "Nayobe",
            "this_week": 34,
            "last_week": 36,
            "peak_position": 34,
            "weeks_on_chart": 4
        },
        {
            "song": "I Want Your Guy (Remix)",
            "artist": "Soul Club",
            "this_week": 35,
            "last_week": 40,
            "peak_position": 35,
            "weeks_on_chart": 4
        },
        {
            "song": "Mutual Attraction (Remix)",
            "artist": "Sylvester",
            "this_week": 36,
            "last_week": 21,
            "peak_position": 10,
            "weeks_on_chart": 8
        },
        {
            "song": "No Reason To Cry (Remix)",
            "artist": "Judy Torres",
            "this_week": 37,
            "last_week": 43,
            "peak_position": 37,
            "weeks_on_chart": 2
        },
        {
            "song": "Can't You Feel My Heart Beat (Remix)",
            "artist": "Claudja Barry",
            "this_week": 38,
            "last_week": 41,
            "peak_position": 38,
            "weeks_on_chart": 4
        },
        {
            "song": "Kiss",
            "artist": "Age Of Chance",
            "this_week": 39,
            "last_week": 35,
            "peak_position": 35,
            "weeks_on_chart": 5
        },
        {
            "song": "Movin' On",
            "artist": "Carolyn Harding",
            "this_week": 40,
            "last_week": 51,
            "peak_position": 40,
            "weeks_on_chart": 1
        },
        {
            "song": "What's Going On (Remix)",
            "artist": "Cyndi Lauper",
            "this_week": 41,
            "last_week": 19,
            "peak_position": 17,
            "weeks_on_chart": 6
        },
        {
            "song": "Back And Forth (Remix)",
            "artist": "Cameo",
            "this_week": 42,
            "last_week": 18,
            "peak_position": 6,
            "weeks_on_chart": 10
        },
        {
            "song": "You're The One",
            "artist": "Sandee",
            "this_week": 43,
            "last_week": 44,
            "peak_position": 43,
            "weeks_on_chart": 3
        },
        {
            "song": "Freakaholic/Living On The Nile",
            "artist": "The Egyptian Lover",
            "this_week": 44,
            "last_week": 46,
            "peak_position": 44,
            "weeks_on_chart": 3
        },
        {
            "song": "Why You Treat Me So Bad (Remix)",
            "artist": "Club Nouveau",
            "this_week": 45,
            "last_week": null,
            "peak_position": 45,
            "weeks_on_chart": 1
        },
        {
            "song": "One Night",
            "artist": "Secret Ties",
            "this_week": 46,
            "last_week": 50,
            "peak_position": 46,
            "weeks_on_chart": 2
        },
        {
            "song": "Keep It Coming",
            "artist": "The Boyd Brothers",
            "this_week": 47,
            "last_week": null,
            "peak_position": 47,
            "weeks_on_chart": 1
        },
        {
            "song": "I Just Died In Your Arms",
            "artist": "Cutting Crew",
            "this_week": 48,
            "last_week": 37,
            "peak_position": 37,
            "weeks_on_chart": 5
        },
        {
            "song": "Only In The Night (Remix)",
            "artist": "The Voice In Fashion",
            "this_week": 49,
            "last_week": 27,
            "peak_position": 8,
            "weeks_on_chart": 10
        },
        {
            "song": "I Wanna Dance With Somebody (Who Loves Me)",
            "artist": "Whitney Houston",
            "this_week": 50,
            "last_week": null,
            "peak_position": 50,
            "weeks_on_chart": 1
        },
        {
            "song": "Funky Town (Remix)",
            "artist": "Pseudo Echo",
            "this_week": 51,
            "last_week": null,
            "peak_position": 51
        },
        {
            "song": "Mean Season",
            "artist": "8th Avenue",
            "this_week": 52,
            "last_week": null,
            "peak_position": 52
        },
        {
            "song": "Outlaw",
            "artist": "Strafe",
            "this_week": 53,
            "last_week": null,
            "peak_position": 53
        },
        {
            "song": "Don't Believe In Love",
            "artist": "Jeanna Cie",
            "this_week": 54,
            "last_week": null,
            "peak_position": 54
        },
        {
            "song": "Lifetime Love",
            "artist": "Joyce Sims",
            "this_week": 55,
            "last_week": null,
            "peak_position": 55
        },
        {
            "song": "Shy Boys",
            "artist": "Ana",
            "this_week": 56,
            "last_week": null,
            "peak_position": 56
        },
        {
            "song": "Lay It On The Line",
            "artist": "Elaine Charles",
            "this_week": 57,
            "last_week": null,
            "peak_position": 57
        }
    ]
}